[1,["ecpdLyjvZBwrvm+cedCcQy","1cVPZ2Yw5O/JfgVUERMMvH","1269d85e6","f2lsmFVLBF0aw+pPV5O5W6","0af28ufLZLtaT3Y9R6GWsb","1chsgSkDhHBYBOt9T5favv","19YbLO5wJFCacYj+oZ08jP","fb0bmLH0xAm5bnth9NxrzC","c2r6VzjeJAcaY58Q0g7p2B","b1p/M19kBHf4p/YUR8PcQo","0fSkr9cNRCSKclnZ+vjcLR","24RtckAS9BtobNh3Dwtr4Y","acRQvzo9lPR51BG+8psHk+"],["node","_spriteFrame","_textureSetter","root","anbgNode","huType","ghostType","tingCardNode","background","data"],[["cc.Node",["_name","_active","_components","_prefab","_contentSize","_parent","_trs","_children"],1,9,4,5,1,7,2],"cc.SpriteFrame",["cc.Sprite",["_sizeMode","node","_materials","_spriteFrame"],2,1,3,6],["cc.PrefabInfo",["fileId","root"],2,1],["cc.Prefab",["_name"],2],["4dcc7ZgWqNB4K04POKIg9Ks",["node","background","tingCardNode","ghostType","huType","anbgNode","anbgSprites"],3,1,1,1,1,1,1,3]],[[3,0,1,2],[2,0,1,2,3,2],[0,0,1,5,2,3,4,6,3],[2,1,2,3,1],[0,0,5,2,3,4,6,2],[4,0,2],[0,0,7,2,3,4,6,2],[0,0,5,2,3,4,2],[0,0,1,5,2,3,4,3],[5,0,1,2,3,4,5,6,1],[3,1,1]],[[[{"name":"tingNode","rect":[37,134,23,31],"offset":[0,0],"originalSize":[23,31],"capInsets":[0,0,0,0]}],[1],0,[0],[2],[2]],[[{"name":"1","rect":[0,0,87,130],"offset":[0,0],"originalSize":[87,130],"capInsets":[0,0,0,0]}],[1],0,[0],[2],[3]],[[{"name":"2","rect":[0,0,87,130],"offset":[0,0],"originalSize":[87,130],"capInsets":[0,0,0,0]}],[1],0,[0],[2],[4]],[[[5,"BottomHandCard"],[6,"BottomHandCard",[-9,-10,-11,-12,-13,-14,-15],[[1,0,-2,[14],15],[9,-8,-7,-6,-5,-4,-3,[16,17]]],[10,-1],[5,84,130],[-508,0,0,0,0,0,1,1,1,1]],[7,"bg",1,[[1,0,-16,[0],1]],[0,"701kRXDgxFPa7lJMgglPEN",1],[5,84,130]],[2,"icon_",false,1,[[1,0,-17,[4],5]],[0,"b3ts5oJ9tFjLLqLsxfqQYy",1],[5,35,24],[-23.586,30.733,0,0,0,0,1,1,1,1]],[2,"icon_hu1",false,1,[[3,-18,[6],7]],[0,"a603k80JpM7L6tTP2wa1tu",1],[5,36,62],[-26,31,0,0,0,0,1,1,1,1]],[8,"anbg",false,1,[[1,0,-19,[10],11]],[0,"7bx1HaYhpOmK4EOMds7OxU",1],[5,87,130]],[4,"icon_ting",1,[[1,0,-20,[12],13]],[0,"b7uVUOJ7NDtrDMx6ogLlwa",1],[5,23,31],[-30.706,49.774,0,0,0,0,1,1,1,1]],[4,"value",1,[[3,-21,[2],3]],[0,"629KcCz/NMUZZi+GL8A9u+",1],[5,35,65],[0,-9,0,0,0,0,1,1.2,1.2,1]],[2,"sanjiao",false,1,[[3,-22,[8],9]],[0,"726O/5hvtOEZF8FSed5ADS",1],[5,63,57],[0,70,0,0,0,0,1,0.5,0.5,1]]],0,[0,3,1,0,0,1,0,4,5,0,5,4,0,6,3,0,7,6,0,8,2,0,0,1,0,-1,2,0,-2,7,0,-3,3,0,-4,4,0,-5,8,0,-6,5,0,-7,6,0,0,2,0,0,3,0,0,4,0,0,5,0,0,6,0,0,7,0,0,8,0,9,1,22],[0,0,0,0,0,0,0,0,0,0,0,0,0,0,0,0,0,0],[-1,1,-1,1,-1,1,-1,1,-1,1,-1,1,-1,1,-1,1,-1,-2],[0,5,0,6,0,7,0,8,0,9,0,1,0,10,0,11,1,12]]]]