[
  1,
  [
    "1588d7a5b",
    "07VtZt6chBn5wN5fEo9oPq",
    "153d88947"
  ],
  [
    "_textureSetter"
  ],
  [
    "cc.SpriteFrame"
  ],
  0,
  [
    [
      [
        {
          "name": "btn_close",
          "rect": [
            3,
            102,
            78,
            78
          ],
          "offset": [
            0,
            1
          ],
          "originalSize": [
            80,
            80
          ],
          "capInsets": [
            0,
            0,
            0,
            0
          ]
        }
      ],
      [
        0
      ],
      0,
      [
        0
      ],
      [
        0
      ],
      [
        0
      ]
    ],
    [
      [
        {
          "name": "btn_detail_3",
          "rect": [
            3,
            186,
            320,
            56
          ],
          "offset": [
            0,
            0
          ],
          "originalSize": [
            320,
            56
          ],
          "capInsets": [
            0,
            0,
            0,
            0
          ]
        }
      ],
      [
        0
      ],
      0,
      [
        0
      ],
      [
        0
      ],
      [
        0
      ]
    ],
    [
      [
        {
          "name": "bg_main",
          "rect": [
            0,
            0,
            1084,
            682
          ],
          "offset": [
            0,
            0
          ],
          "originalSize": [
            1084,
            682
          ],
          "capInsets": [
            0,
            0,
            0,
            0
          ]
        }
      ],
      [
        0
      ],
      0,
      [
        0
      ],
      [
        0
      ],
      [
        1
      ]
    ],
    [
      [
        {
          "name": "1",
          "rect": [
            119,
            3,
            97,
            78
          ],
          "offset": [
            0,
            -0.5
          ],
          "originalSize": [
            97,
            79
          ],
          "rotated": 1,
          "capInsets": [
            0,
            0,
            0,
            0
          ]
        }
      ],
      [
        0
      ],
      0,
      [
        0
      ],
      [
        0
      ],
      [
        0
      ]
    ],
    [
      [
        {
          "name": "img_x",
          "rect": [
            3,
            3,
            25,
            27
          ],
          "offset": [
            0,
            0
          ],
          "originalSize": [
            25,
            27
          ],
          "capInsets": [
            0,
            0,
            0,
            0
          ]
        }
      ],
      [
        0
      ],
      0,
      [
        0
      ],
      [
        0
      ],
      [
        0
      ]
    ],
    [
      [
        {
          "name": "img_gold",
          "rect": [
            34,
            3,
            49,
            49
          ],
          "offset": [
            0,
            0
          ],
          "originalSize": [
            55,
            57
          ],
          "capInsets": [
            0,
            0,
            0,
            0
          ]
        }
      ],
      [
        0
      ],
      0,
      [
        0
      ],
      [
        0
      ],
      [
        0
      ]
    ],
    [
      [
        {
          "name": "bg_right",
          "rect": [
            3,
            3,
            640,
            550
          ],
          "offset": [
            0,
            0
          ],
          "originalSize": [
            640,
            550
          ],
          "capInsets": [
            0,
            0,
            0,
            0
          ]
        }
      ],
      [
        0
      ],
      0,
      [
        0
      ],
      [
        0
      ],
      [
        2
      ]
    ],
    [
      [
        {
          "name": "btn_detail_1",
          "rect": [
            3,
            248,
            320,
            56
          ],
          "offset": [
            0,
            0
          ],
          "originalSize": [
            320,
            56
          ],
          "capInsets": [
            0,
            0,
            0,
            0
          ]
        }
      ],
      [
        0
      ],
      0,
      [
        0
      ],
      [
        0
      ],
      [
        0
      ]
    ],
    [
      [
        {
          "name": "img_title",
          "rect": [
            87,
            106,
            259,
            46
          ],
          "offset": [
            0,
            0
          ],
          "originalSize": [
            259,
            46
          ],
          "capInsets": [
            0,
            0,
            0,
            0
          ]
        }
      ],
      [
        0
      ],
      0,
      [
        0
      ],
      [
        0
      ],
      [
        0
      ]
    ],
    [
      [
        {
          "name": "bg_left",
          "rect": [
            3,
            372,
            373,
            550
          ],
          "offset": [
            0,
            0
          ],
          "originalSize": [
            373,
            550
          ],
          "rotated": 1,
          "capInsets": [
            0,
            0,
            0,
            0
          ]
        }
      ],
      [
        0
      ],
      0,
      [
        0
      ],
      [
        0
      ],
      [
        0
      ]
    ],
    [
      [
        {
          "name": "btn_rule_1",
          "rect": [
            3,
            310,
            320,
            56
          ],
          "offset": [
            0,
            0
          ],
          "originalSize": [
            320,
            56
          ],
          "capInsets": [
            0,
            0,
            0,
            0
          ]
        }
      ],
      [
        0
      ],
      0,
      [
        0
      ],
      [
        0
      ],
      [
        0
      ]
    ],
    [
      [
        {
          "name": "img_reward",
          "rect": [
            3,
            58,
            110,
            38
          ],
          "offset": [
            0,
            0
          ],
          "originalSize": [
            110,
            38
          ],
          "capInsets": [
            0,
            0,
            0,
            0
          ]
        }
      ],
      [
        0
      ],
      0,
      [
        0
      ],
      [
        0
      ],
      [
        0
      ]
    ],
    [
      [
        {
          "name": "btn_rule_3",
          "rect": [
            352,
            3,
            320,
            56
          ],
          "offset": [
            0,
            0
          ],
          "originalSize": [
            320,
            56
          ],
          "rotated": 1,
          "capInsets": [
            0,
            0,
            0,
            0
          ]
        }
      ],
      [
        0
      ],
      0,
      [
        0
      ],
      [
        0
      ],
      [
        0
      ]
    ]
  ]
]